blackducklib/__init__.py
blackducklib/blackduck.py
blackducklib/blackducklib.py
blackducklib-0.0.2.dist-info/LICENSE.txt
blackducklib-0.0.2.dist-info/METADATA
blackducklib-0.0.2.dist-info/WHEEL
blackducklib-0.0.2.dist-info/top_level.txt
blackducklib-0.0.2.dist-info/RECORD
