Metadata-Version: 2.1
Name: blackducklib
Version: 0.0.2
Summary: Library to execute bd commands
Home-page: UNKNOWN
Author: Ritesh M
Author-email: mailriteshm@gmail.com
License: MIT
Platform: UNKNOWN
Classifier: Development Status :: 5 - Production/Stable
Classifier: Intended Audience :: Education
Classifier: Operating System :: Microsoft :: Windows :: Windows 10
Classifier: License :: OSI Approved :: MIT License
Classifier: Programming Language :: Python :: 3
